codedevdb/__init__.py
codedevdb-0.3.dist-info/licenses/LICENSE.txt
codedevdb-0.3.dist-info/METADATA
codedevdb-0.3.dist-info/WHEEL
codedevdb-0.3.dist-info/top_level.txt
codedevdb-0.3.dist-info/RECORD
