Metadata-Version: 2.4
Name: codedevdb
Version: 0.3
Summary: A library dedicated to easy and seamless handling of sqlite3 / db files
Home-page: https://t.me/midoghanam
Author: CodeDev Company
Author-email: CodeDev Company <codedev.eg@hotmail.com>, Mohamed Ahmed Ghanam <mghanam883@outlook.com>
License: MIT
Project-URL: Homepage, https://t.me/mido_ghanam
Project-URL: My_Telegram_Account, https://t.me/midoghanam
Project-URL: EgyptianProgrammers, https://t.me/egyptionprogrammers
Project-URL: Whatsapp, https://wa.me/201101023681
Requires-Python: >=3.6
License-File: LICENSE.txt
Dynamic: author
Dynamic: home-page
Dynamic: license-file
Dynamic: requires-python
